explainn/__init__.py
explainn/test.py
explainn/interpretation/__init__.py
explainn/interpretation/interpretation.py
explainn/models/__init__.py
explainn/models/networks.py
explainn/train/__init__.py
explainn/train/test.py
explainn/train/train.py
explainn/utils/__init__.py
explainn/utils/tools.py
explainn-0.1.5.dist-info/METADATA
explainn-0.1.5.dist-info/WHEEL
explainn-0.1.5.dist-info/top_level.txt
explainn-0.1.5.dist-info/RECORD
