Metadata-Version: 2.1
Name: explainn
Version: 0.1.5
Summary: interpretable and transparent neural networks for genomics
Home-page: UNKNOWN
Author: Gherman Novakovsky @ wassermanlab
Author-email: gnovakovsky@cmmt.ubc.ca
License: MIT
Platform: UNKNOWN
Classifier: Intended Audience :: Developers
Classifier: License :: OSI Approved :: MIT License
Classifier: Programming Language :: Python
Classifier: Programming Language :: Python :: 3
Classifier: Programming Language :: Python :: 3.6
Classifier: Programming Language :: Python :: 3.7
Classifier: Programming Language :: Python :: 3.8
Classifier: Programming Language :: Python :: 3.9
Classifier: Operating System :: OS Independent
Requires-Dist: numpy
Requires-Dist: h5py
Requires-Dist: tqdm
Requires-Dist: pandas
